dc2host/__init__.py
dc2host/__main__.py
dc2host/app.py
dc2host/cli.py
dc2host/helpers.py
dc2host-1.0.0.dist-info/LICENSE
dc2host-1.0.0.dist-info/METADATA
dc2host-1.0.0.dist-info/WHEEL
dc2host-1.0.0.dist-info/top_level.txt
dc2host-1.0.0.dist-info/RECORD
