Metadata-Version: 2.1
Name: dc2host
Version: 1.0.0
Summary: VS Code Dev Containers integration with a host system
Author-email: Vlad Folts <vladfolts@gmail.com>
Project-URL: Homepage, https://github.com/vladfolts/dc2host
Classifier: Programming Language :: Python :: 3
Classifier: License :: OSI Approved :: MIT License
Classifier: Operating System :: OS Independent
Requires-Python: >=3.8
License-File: LICENSE
Requires-Dist: docker
Requires-Dist: flask
Requires-Dist: GitPython
Provides-Extra: test
Requires-Dist: types-docker ; extra == 'test'
Requires-Dist: mypy ; extra == 'test'
Requires-Dist: pytest ; extra == 'test'
